Qpai/__init__.py
Qpai/test_one.py
Qpai/test_trial.py
Qpai/ViT/ViTclassifier.py
Qpai/ViT/__init__.py
Qpai-0.0.3.dist-info/LICENSE
Qpai-0.0.3.dist-info/METADATA
Qpai-0.0.3.dist-info/WHEEL
Qpai-0.0.3.dist-info/top_level.txt
Qpai-0.0.3.dist-info/RECORD
