Metadata-Version: 2.1
Name: Qpai
Version: 0.0.3
Summary: Qpai
Author: Aniket Guchhait
Author-email: aniket.emailme@gmail.com
Keywords: quantum,machine learning,quantum computing,qiskit,quantum machine learning
Classifier: Development Status :: 1 - Planning
Classifier: Intended Audience :: Developers
Classifier: Programming Language :: Python :: 3
Classifier: Operating System :: Unix
Classifier: Operating System :: MacOS :: MacOS X
Classifier: Operating System :: Microsoft :: Windows
License-File: LICENSE
Requires-Dist: transformer-implementations
Requires-Dist: numpy
Requires-Dist: torchvision
